roughviz/__init__.py
roughviz/roughviz.py
roughviz/templates/bar.html
roughviz/templates/barh.html
roughviz/templates/donut.html
roughviz/templates/pie.html
roughviz/templates/stackedbar.html
roughviz-4.7.0.dist-info/LICENSE
roughviz-4.7.0.dist-info/METADATA
roughviz-4.7.0.dist-info/WHEEL
roughviz-4.7.0.dist-info/top_level.txt
roughviz-4.7.0.dist-info/RECORD
