Metadata-Version: 2.1
Name: roughviz
Version: 4.7.0
Summary: A python visualization library for creating sketchy/hand-drawn styled charts.
Home-page: https://github.com/hannansatopay/roughviz
Author: Hannan Satopay
Author-email: sathannan@hotmail.com
License: MIT
Platform: UNKNOWN
Classifier: Development Status :: 5 - Production/Stable
Classifier: Framework :: IPython
Classifier: Programming Language :: Python :: 3
Classifier: License :: OSI Approved :: MIT License
Classifier: Operating System :: OS Independent
Requires-Python: >=3.6
Requires-Dist: Jinja2
Requires-Dist: pandas
